LICENSE
MANIFEST.in
README.md
setup.py
django_sparkle_1.5.egg-info/PKG-INFO
django_sparkle_1.5.egg-info/SOURCES.txt
django_sparkle_1.5.egg-info/dependency_links.txt
django_sparkle_1.5.egg-info/not-zip-safe
django_sparkle_1.5.egg-info/requires.txt
django_sparkle_1.5.egg-info/top_level.txt
sparkle/__init__.py
sparkle/__init__.pyc
sparkle/admin.py
sparkle/admin.pyc
sparkle/conf.py
sparkle/conf.pyc
sparkle/models.py
sparkle/models.pyc
sparkle/tests.py
sparkle/urls.py
sparkle/urls.pyc
sparkle/views.py
sparkle/views.pyc
sparkle/migrations/0001_initial.py
sparkle/migrations/0001_initial.pyc
sparkle/migrations/0002_auto__chg_field_version_short_version.py
sparkle/migrations/0002_auto__chg_field_version_short_version.pyc
sparkle/migrations/0003_auto__add_field_version_active.py
sparkle/migrations/0003_auto__add_field_version_active.pyc
sparkle/migrations/0004_auto__add_field_application_slug.py
sparkle/migrations/0004_auto__add_field_application_slug.pyc
sparkle/migrations/0005_add_published__add_created.py
sparkle/migrations/0005_add_published__add_created.pyc
sparkle/migrations/0006__data_migration.py
sparkle/migrations/0006__data_migration.pyc
sparkle/migrations/0007__del_field_version_active__del_field_version_published.py
sparkle/migrations/0007__del_field_version_active__del_field_version_published.pyc
sparkle/migrations/__init__.py
sparkle/migrations/__init__.pyc
sparkle/templates/sparkle/appcast.xml